libtempo_py.cp36-win_amd64.pyd
libtempo_py-1.0.0.dist-info/METADATA
libtempo_py-1.0.0.dist-info/RECORD
libtempo_py-1.0.0.dist-info/WHEEL
libtempo_py-1.0.0.dist-info/top_level.txt
