Metadata-Version: 2.1
Name: libtempo-py
Version: 1.0.0
Summary: C++ / Python library with signal processing and tempo estimation utilities.
Home-page: https://github.com/EgorDm/libtempo
Author: Egor Dmitriev
Author-email: egordmitriev@gmail.com
License: MIT
Platform: UNKNOWN
Classifier: Programming Language :: Python :: 3
Classifier: License :: OSI Approved :: MIT License
Classifier: Topic :: Multimedia :: Sound/Audio :: Analysis
